pypdd.py
pypdd-0.3.1.data/scripts/pypdd.py
pypdd-0.3.1.dist-info/COPYING
pypdd-0.3.1.dist-info/METADATA
pypdd-0.3.1.dist-info/WHEEL
pypdd-0.3.1.dist-info/top_level.txt
pypdd-0.3.1.dist-info/RECORD
