Metadata-Version: 2.1
Name: pypdd
Version: 0.3.1
Summary: A positive degree day model for glacier surface mass balance
Home-page: http://github.com/juseg/aftershocks
Author: Julien Seguinot
Author-email: seguinot@vaw.baug.ethz.ch
License: gpl-3.0
Platform: UNKNOWN
Requires-Dist: numpy
Requires-Dist: scipy
Provides-Extra: netcdf_interface
Requires-Dist: netCDF4 ; extra == 'netcdf_interface'
